{
  "name": "Casco antiguo de Ciutadella",
  "lang": "es",
  "translationKey": "casco-antiguo-de-ciutadella",
  "type": "otro",
  "description": "La antigua capital, casco historico de palacios senoriales, la Catedral gotica, la plaza des Born, Ses Voltes, el Mercat des Peix y un puerto encajonado lleno de restaurantes. La cara mas aristocratica y elegante de Meno",
  "coordinates": {
    "lat": 40.0014,
    "lng": 3.8419
  },
  "area": "Oeste (Ciutadella)",
  "tags": [
    "oeste",
    "nucleo",
    "ciutadella"
  ],
  "status": "draft",
  "planner": {
    "zone": "oeste",
    "cluster": "ciutadella-ciudad",
    "plannerType": "pueblo",
    "idealFor": [
      "cultura",
      "gastronomia",
      "parejas",
      "naturaleza",
      "lujo-tranquilo",
      "familias"
    ],
    "durationMin": 180,
    "carAccess": "sin-coche-ok",
    "busServed": true,
    "carAccessClosedSummer": false,
    "effortLevel": "A2",
    "isIndoor": false,
    "weatherProof": "exterior",
    "needsReservation": false,
    "dataCertainty": "alta",
    "lastVerified": "2026-06-22"
  }
}
