{
  "name": "Restaurante Smoix",
  "lang": "en",
  "translationKey": "restaurante-smoix",
  "type": "restaurante",
  "description": "A Bib Gourmand distinction from the Michelin Guide held since 2023 and a Repsol Guide Sol it has kept after moving to the Hotel Rural Sant Ignasi, an 18th-century estate on the Cala Morell road about 3 km outside Ciutadella. Mediterranean cooking built on local produce, with refined technique and international touches, from chef Miquel Sánchez. The west of the island's fine-dining stop with real judgement, now set among holm oaks and countryside.",
  "coordinates": {
    "lat": 40.0255,
    "lng": 3.8653
  },
  "area": "West (Ciutadella)",
  "tags": [
    "oeste",
    "gastronomia",
    "ciutadella"
  ],
  "status": "published",
  "planner": {
    "zone": "oeste",
    "cluster": "ciutadella-ciudad",
    "plannerType": "cena",
    "idealFor": [
      "gastronomia",
      "lujo-tranquilo",
      "parejas",
      "cultura"
    ],
    "durationMin": 120,
    "carAccess": "coche-directo",
    "busServed": false,
    "carAccessClosedSummer": false,
    "effortLevel": "A2",
    "isIndoor": false,
    "weatherProof": "exterior",
    "needsReservation": true,
    "dataCertainty": "alta",
    "lastVerified": "2026-07-22",
    "highlights": [
      "a Bib Gourmand table in the Michelin Guide since 2023, plus a Repsol Guide Sol",
      "Mediterranean cooking of organic, seasonal produce",
      "book ahead; it sits at the Hotel Rural Sant Ignasi on the Cala Morell road (~3 km from Ciutadella)"
    ],
    "officialUrl": "https://www.smoix.com/"
  }
}
