{
  "name": "Restaurante Es Cranc",
  "lang": "en",
  "translationKey": "restaurante-es-cranc",
  "type": "restaurante",
  "description": "One of Menorca's most emblematic and traditional restaurants for lobster stew in Fornells, recommended by the Michelin Guide 2026 (one of eleven on the island). It keeps its own tank of local lobsters, chosen on the spot. A slightly lighter version than Sa Llagosta.",
  "coordinates": {
    "lat": 40.05,
    "lng": 4.13
  },
  "area": "North (Es Mercadal)",
  "tags": [
    "norte",
    "gastronomia",
    "es-mercadal"
  ],
  "status": "draft",
  "planner": {
    "zone": "norte",
    "cluster": "fornells-cavalleria",
    "plannerType": "cena",
    "idealFor": [
      "gastronomia",
      "parejas",
      "lujo-tranquilo",
      "familias"
    ],
    "durationMin": 150,
    "carAccess": "coche-directo",
    "busServed": true,
    "carAccessClosedSummer": false,
    "effortLevel": "A2",
    "isIndoor": false,
    "weatherProof": "exterior",
    "needsReservation": true,
    "dataCertainty": "alta",
    "lastVerified": "2026-06-22"
  }
}
