{
  "name": "Trepuco",
  "lang": "es",
  "translationKey": "trepuco",
  "type": "monumento",
  "description": "Poblado talayótico (UNESCO) con una de las taulas más grandes y mejor conservadas de la isla (4,8 m de altura), dentro de un recinto fortificado decimononico. Muy cercano a Maó, ideal como primera toma de contacto con la cultura talayótica.",
  "coordinates": {
    "lat": 39.8703,
    "lng": 4.2719
  },
  "area": "Este (Es Castell)",
  "tags": [
    "este",
    "yacimiento",
    "es-castell"
  ],
  "status": "draft",
  "planner": {
    "zone": "este",
    "cluster": "mao-puerto",
    "plannerType": "yacimiento",
    "idealFor": [
      "cultura",
      "naturaleza"
    ],
    "durationMin": 38,
    "carAccess": "coche-directo",
    "busServed": false,
    "carAccessClosedSummer": false,
    "effortLevel": "B",
    "isIndoor": false,
    "weatherProof": "exterior",
    "needsReservation": false,
    "dataCertainty": "media",
    "lastVerified": "2026-06-22",
    "highlights": [
      "una de las taulas más grandes de la isla (4,8 m), muy cerca de Maó",
      "el recinto talayótico fortificado (Patrimonio Mundial UNESCO)",
      "una visita corta de cultura talayótica sin alejarse de la capital"
    ]
  }
}
