{
  "title": "Molí Market, Sant Lluís",
  "lang": "en",
  "translationKey": "moli-market-sant-lluis",
  "startDate": "2026-06-19",
  "endDate": "2026-08-14",
  "location": "Carrer de Sant Lluís (zona del molino), Sant Lluís",
  "category": "mercado",
  "description": "Sant Lluís's Molí Market is a summer market held on certain Friday evenings (roughly 19:00 to 23:00), usually every fortnight between June and August, with crafts and local offerings around the village windmill. Exact 2026 dates to be confirmed with Sant Lluís town council.",
  "tags": [
    "mercado",
    "Sant Lluís",
    "nocturno",
    "verano",
    "quincenal",
    "Molí Market"
  ],
  "sourceUrl": "https://apuntmenorca.com/compras/mercados-de-menorca/",
  "status": "published",
  "source": "auto-agenda",
  "image": "/uploads/ag-moli-market-sant-lluis.webp"
}
